[
  {
    "goals": "0",
    "shots": "0",
    "xG": "0",
    "time": "64",
    "position": "DMR",
    "h_team": "Union Berlin",
    "a_team": "FC Cologne",
    "h_goals": "2",
    "a_goals": "2",
    "date": "2026-05-02",
    "id": "30510",
    "season": "2025",
    "roster_id": "787097",
    "xA": "0",
    "assists": "0",
    "key_passes": "0",
    "npg": "0",
    "npxG": "0",
    "xGChain": "0.033547934144735336",
    "xGBuildup": "0.033547934144735336"
  },
  {
    "goals": "0",
    "shots": "0",
    "xG": "0",
    "time": "27",
    "position": "Sub",
    "h_team": "RasenBallsport Leipzig",
    "a_team": "Union Berlin",
    "h_goals": "3",
    "a_goals": "1",
    "date": "2026-04-24",
    "id": "30500",
    "season": "2025",
    "roster_id": "785001",
    "xA": "0.32466375827789307",
    "assists": "1",
    "key_passes": "2",
    "npg": "0",
    "npxG": "0",
    "xGChain": "0",
    "xGBuildup": "0"
  },
  {
    "goals": "0",
    "shots": "0",
    "xG": "0",
    "time": "13",
    "position": "Sub",
    "h_team": "Bayern Munich",
    "a_team": "Union Berlin",
    "h_goals": "4",
    "a_goals": "0",
    "date": "2026-03-21",
    "id": "30459",
    "season": "2025",
    "roster_id": "778483",
    "xA": "0",
    "assists": "0",
    "key_passes": "0",
    "npg": "0",
    "npxG": "0",
    "xGChain": "0",
    "xGBuildup": "0"
  },
  {
    "goals": "0",
    "shots": "0",
    "xG": "0",
    "time": "10",
    "position": "Sub",
    "h_team": "Freiburg",
    "a_team": "Union Berlin",
    "h_goals": "0",
    "a_goals": "1",
    "date": "2026-03-15",
    "id": "30453",
    "season": "2025",
    "roster_id": "777673",
    "xA": "0",
    "assists": "0",
    "key_passes": "0",
    "npg": "0",
    "npxG": "0",
    "xGChain": "0",
    "xGBuildup": "0"
  },
  {
    "goals": "0",
    "shots": "1",
    "xG": "0.04508184269070625",
    "time": "70",
    "position": "DML",
    "h_team": "Union Berlin",
    "a_team": "Borussia Dortmund",
    "h_goals": "0",
    "a_goals": "3",
    "date": "2026-01-24",
    "id": "30394",
    "season": "2025",
    "roster_id": "765812",
    "xA": "0.5601836442947388",
    "assists": "0",
    "key_passes": "5",
    "npg": "0",
    "npxG": "0.04508184269070625",
    "xGChain": "0.021048136055469513",
    "xGBuildup": "0"
  },
  {
    "goals": "0",
    "shots": "1",
    "xG": "0.015210193581879139",
    "time": "70",
    "position": "DML",
    "h_team": "VfB Stuttgart",
    "a_team": "Union Berlin",
    "h_goals": "1",
    "a_goals": "1",
    "date": "2026-01-18",
    "id": "30383",
    "season": "2025",
    "roster_id": "764783",
    "xA": "0.1819872111082077",
    "assists": "0",
    "key_passes": "3",
    "npg": "0",
    "npxG": "0.015210193581879139",
    "xGChain": "0.14176781475543976",
    "xGBuildup": "0.02780618518590927"
  },
  {
    "goals": "0",
    "shots": "0",
    "xG": "0",
    "time": "16",
    "position": "Sub",
    "h_team": "FC Cologne",
    "a_team": "Union Berlin",
    "h_goals": "0",
    "a_goals": "1",
    "date": "2025-12-20",
    "id": "30352",
    "season": "2025",
    "roster_id": "759020",
    "xA": "0",
    "assists": "0",
    "key_passes": "0",
    "npg": "0",
    "npxG": "0",
    "xGChain": "0.1902894228696823",
    "xGBuildup": "0.1902894228696823"
  },
  {
    "goals": "0",
    "shots": "1",
    "xG": "0.018234293907880783",
    "time": "15",
    "position": "Sub",
    "h_team": "Union Berlin",
    "a_team": "Bayern Munich",
    "h_goals": "2",
    "a_goals": "2",
    "date": "2025-11-08",
    "id": "30312",
    "season": "2025",
    "roster_id": "750048",
    "xA": "0",
    "assists": "0",
    "key_passes": "0",
    "npg": "0",
    "npxG": "0.018234293907880783",
    "xGChain": "0.018234293907880783",
    "xGBuildup": "0"
  },
  {
    "goals": "0",
    "shots": "0",
    "xG": "0",
    "time": "1",
    "position": "Sub",
    "h_team": "Union Berlin",
    "a_team": "VfB Stuttgart",
    "h_goals": "2",
    "a_goals": "1",
    "date": "2025-08-23",
    "id": "30227",
    "season": "2025",
    "roster_id": "733176",
    "xA": "0.09793679416179657",
    "assists": "0",
    "key_passes": "1",
    "npg": "0",
    "npxG": "0",
    "xGChain": "0",
    "xGBuildup": "0"
  },
  {
    "goals": "0",
    "shots": "0",
    "xG": "0",
    "time": "62",
    "position": "DML",
    "h_team": "Augsburg",
    "a_team": "Union Berlin",
    "h_goals": "1",
    "a_goals": "2",
    "date": "2025-05-17",
    "id": "28044",
    "season": "2024",
    "roster_id": "727678",
    "xA": "0",
    "assists": "0",
    "key_passes": "0",
    "npg": "0",
    "npxG": "0",
    "xGChain": "0.020016247406601906",
    "xGBuildup": "0.020016247406601906"
  },
  {
    "goals": "0",
    "shots": "1",
    "xG": "0.012357712723314762",
    "time": "26",
    "position": "Sub",
    "h_team": "Union Berlin",
    "a_team": "FC Heidenheim",
    "h_goals": "0",
    "a_goals": "3",
    "date": "2025-05-10",
    "id": "28036",
    "season": "2024",
    "roster_id": "725627",
    "xA": "0.029127368703484535",
    "assists": "0",
    "key_passes": "1",
    "npg": "0",
    "npxG": "0.012357712723314762",
    "xGChain": "0.04148508235812187",
    "xGBuildup": "0.012357712723314762"
  },
  {
    "goals": "0",
    "shots": "0",
    "xG": "0",
    "time": "85",
    "position": "DML",
    "h_team": "Bayer Leverkusen",
    "a_team": "Union Berlin",
    "h_goals": "0",
    "a_goals": "0",
    "date": "2025-04-12",
    "id": "27994",
    "season": "2024",
    "roster_id": "718584",
    "xA": "0",
    "assists": "0",
    "key_passes": "0",
    "npg": "0",
    "npxG": "0",
    "xGChain": "0",
    "xGBuildup": "0"
  },
  {
    "goals": "0",
    "shots": "1",
    "xG": "0.05047440156340599",
    "time": "90",
    "position": "DML",
    "h_team": "Union Berlin",
    "a_team": "Wolfsburg",
    "h_goals": "1",
    "a_goals": "0",
    "date": "2025-04-06",
    "id": "27991",
    "season": "2024",
    "roster_id": "717824",
    "xA": "0.13384762406349182",
    "assists": "0",
    "key_passes": "3",
    "npg": "0",
    "npxG": "0.05047440156340599",
    "xGChain": "0.05680448189377785",
    "xGBuildup": "0.01617486961185932"
  },
  {
    "goals": "0",
    "shots": "0",
    "xG": "0",
    "time": "90",
    "position": "DML",
    "h_team": "Freiburg",
    "a_team": "Union Berlin",
    "h_goals": "1",
    "a_goals": "2",
    "date": "2025-03-30",
    "id": "27982",
    "season": "2024",
    "roster_id": "715422",
    "xA": "0",
    "assists": "0",
    "key_passes": "0",
    "npg": "0",
    "npxG": "0",
    "xGChain": "0.07497497648000717",
    "xGBuildup": "0.07497497648000717"
  },
  {
    "goals": "0",
    "shots": "2",
    "xG": "0.10010750591754913",
    "time": "90",
    "position": "DL",
    "h_team": "Union Berlin",
    "a_team": "Bayern Munich",
    "h_goals": "1",
    "a_goals": "1",
    "date": "2025-03-15",
    "id": "27973",
    "season": "2024",
    "roster_id": "712835",
    "xA": "0.024598296731710434",
    "assists": "0",
    "key_passes": "1",
    "npg": "0",
    "npxG": "0.10010750591754913",
    "xGChain": "0.08954323828220367",
    "xGBuildup": "0.024598296731710434"
  },
  {
    "goals": "0",
    "shots": "1",
    "xG": "0.05076594650745392",
    "time": "90",
    "position": "DML",
    "h_team": "Eintracht Frankfurt",
    "a_team": "Union Berlin",
    "h_goals": "1",
    "a_goals": "2",
    "date": "2025-03-09",
    "id": "27961",
    "season": "2024",
    "roster_id": "712017",
    "xA": "0.10818575322628021",
    "assists": "0",
    "key_passes": "2",
    "npg": "0",
    "npxG": "0.05076594650745392",
    "xGChain": "0.21468020975589752",
    "xGBuildup": "0.1639142632484436"
  },
  {
    "goals": "0",
    "shots": "0",
    "xG": "0",
    "time": "90",
    "position": "DMR",
    "h_team": "Union Berlin",
    "a_team": "Holstein Kiel",
    "h_goals": "0",
    "a_goals": "1",
    "date": "2025-03-02",
    "id": "27955",
    "season": "2024",
    "roster_id": "710351",
    "xA": "0.32063645124435425",
    "assists": "0",
    "key_passes": "6",
    "npg": "0",
    "npxG": "0",
    "xGChain": "0.18845286965370178",
    "xGBuildup": "0.047481607645750046"
  },
  {
    "goals": "0",
    "shots": "0",
    "xG": "0",
    "time": "90",
    "position": "DR",
    "h_team": "Borussia Dortmund",
    "a_team": "Union Berlin",
    "h_goals": "6",
    "a_goals": "0",
    "date": "2025-02-22",
    "id": "27942",
    "season": "2024",
    "roster_id": "708056",
    "xA": "0.12953995168209076",
    "assists": "0",
    "key_passes": "2",
    "npg": "0",
    "npxG": "0",
    "xGChain": "0",
    "xGBuildup": "0"
  },
  {
    "goals": "0",
    "shots": "0",
    "xG": "0",
    "time": "90",
    "position": "DR",
    "h_team": "Union Berlin",
    "a_team": "Borussia M.Gladbach",
    "h_goals": "1",
    "a_goals": "2",
    "date": "2025-02-15",
    "id": "27937",
    "season": "2024",
    "roster_id": "706089",
    "xA": "0.24654115736484528",
    "assists": "0",
    "key_passes": "4",
    "npg": "0",
    "npxG": "0",
    "xGChain": "0.26228681206703186",
    "xGBuildup": "0.26228681206703186"
  },
  {
    "goals": "0",
    "shots": "0",
    "xG": "0",
    "time": "79",
    "position": "DR",
    "h_team": "Hoffenheim",
    "a_team": "Union Berlin",
    "h_goals": "0",
    "a_goals": "4",
    "date": "2025-02-08",
    "id": "27925",
    "season": "2024",
    "roster_id": "704730",
    "xA": "0.469292551279068",
    "assists": "0",
    "key_passes": "2",
    "npg": "0",
    "npxG": "0",
    "xGChain": "1.0848177671432495",
    "xGBuildup": "0.6155252456665039"
  },
  {
    "goals": "0",
    "shots": "1",
    "xG": "0.010836459696292877",
    "time": "72",
    "position": "DR",
    "h_team": "Union Berlin",
    "a_team": "RasenBallsport Leipzig",
    "h_goals": "0",
    "a_goals": "0",
    "date": "2025-02-01",
    "id": "27913",
    "season": "2024",
    "roster_id": "703603",
    "xA": "0.050254639238119125",
    "assists": "0",
    "key_passes": "2",
    "npg": "0",
    "npxG": "0.010836459696292877",
    "xGChain": "0.24995818734169006",
    "xGBuildup": "0.21272984147071838"
  },
  {
    "goals": "0",
    "shots": "0",
    "xG": "0",
    "time": "90",
    "position": "DMR",
    "h_team": "St. Pauli",
    "a_team": "Union Berlin",
    "h_goals": "3",
    "a_goals": "0",
    "date": "2025-01-26",
    "id": "27907",
    "season": "2024",
    "roster_id": "702253",
    "xA": "0.32476431131362915",
    "assists": "0",
    "key_passes": "1",
    "npg": "0",
    "npxG": "0",
    "xGChain": "0.3851228356361389",
    "xGBuildup": "0.06035852059721947"
  },
  {
    "goals": "0",
    "shots": "0",
    "xG": "0",
    "time": "62",
    "position": "DMR",
    "h_team": "Union Berlin",
    "a_team": "Mainz 05",
    "h_goals": "2",
    "a_goals": "1",
    "date": "2025-01-19",
    "id": "27901",
    "season": "2024",
    "roster_id": "700629",
    "xA": "0.40921029448509216",
    "assists": "0",
    "key_passes": "2",
    "npg": "0",
    "npxG": "0",
    "xGChain": "0.47400930523872375",
    "xGBuildup": "0.06479901075363159"
  },
  {
    "goals": "0",
    "shots": "1",
    "xG": "0.04647313430905342",
    "time": "40",
    "position": "Sub",
    "h_team": "Werder Bremen",
    "a_team": "Union Berlin",
    "h_goals": "4",
    "a_goals": "1",
    "date": "2024-12-21",
    "id": "27873",
    "season": "2024",
    "roster_id": "695224",
    "xA": "0",
    "assists": "0",
    "key_passes": "0",
    "npg": "0",
    "npxG": "0.04647313430905342",
    "xGChain": "0.05954105779528618",
    "xGBuildup": "0.05954105779528618"
  },
  {
    "goals": "0",
    "shots": "0",
    "xG": "0",
    "time": "4",
    "position": "Sub",
    "h_team": "VfB Stuttgart",
    "a_team": "Union Berlin",
    "h_goals": "3",
    "a_goals": "2",
    "date": "2024-12-06",
    "id": "27851",
    "season": "2024",
    "roster_id": "691753",
    "xA": "0",
    "assists": "0",
    "key_passes": "0",
    "npg": "0",
    "npxG": "0",
    "xGChain": "0",
    "xGBuildup": "0"
  },
  {
    "goals": "0",
    "shots": "0",
    "xG": "0",
    "time": "10",
    "position": "Sub",
    "h_team": "Union Berlin",
    "a_team": "Bayer Leverkusen",
    "h_goals": "1",
    "a_goals": "2",
    "date": "2024-11-30",
    "id": "27848",
    "season": "2024",
    "roster_id": "689909",
    "xA": "0.08814298361539841",
    "assists": "0",
    "key_passes": "1",
    "npg": "0",
    "npxG": "0",
    "xGChain": "0",
    "xGBuildup": "0"
  },
  {
    "goals": "0",
    "shots": "1",
    "xG": "0.75777667760849",
    "time": "86",
    "position": "DML",
    "h_team": "Union Berlin",
    "a_team": "Freiburg",
    "h_goals": "2",
    "a_goals": "1",
    "date": "2024-05-18",
    "id": "23363",
    "season": "2023",
    "roster_id": "662526",
    "xA": "0",
    "assists": "0",
    "key_passes": "0",
    "npg": "0",
    "npxG": "0",
    "xGChain": "0.11101102083921432",
    "xGBuildup": "0.11101102083921432"
  },
  {
    "goals": "0",
    "shots": "1",
    "xG": "0.012379175052046776",
    "time": "13",
    "position": "Sub",
    "h_team": "FC Cologne",
    "a_team": "Union Berlin",
    "h_goals": "3",
    "a_goals": "2",
    "date": "2024-05-11",
    "id": "23358",
    "season": "2023",
    "roster_id": "660435",
    "xA": "0.05195624753832817",
    "assists": "0",
    "key_passes": "2",
    "npg": "0",
    "npxG": "0.012379175052046776",
    "xGChain": "0.42461976408958435",
    "xGBuildup": "0.412240594625473"
  },
  {
    "goals": "0",
    "shots": "1",
    "xG": "0.011202528141438961",
    "time": "90",
    "position": "DMR",
    "h_team": "Union Berlin",
    "a_team": "Bochum",
    "h_goals": "3",
    "a_goals": "4",
    "date": "2024-05-05",
    "id": "23345",
    "season": "2023",
    "roster_id": "659482",
    "xA": "0.2020706981420517",
    "assists": "0",
    "key_passes": "4",
    "npg": "0",
    "npxG": "0.011202528141438961",
    "xGChain": "0.011202528141438961",
    "xGBuildup": "0"
  },
  {
    "goals": "0",
    "shots": "0",
    "xG": "0",
    "time": "87",
    "position": "MR",
    "h_team": "Borussia M.Gladbach",
    "a_team": "Union Berlin",
    "h_goals": "0",
    "a_goals": "0",
    "date": "2024-04-28",
    "id": "23340",
    "season": "2023",
    "roster_id": "657686",
    "xA": "0.09427335113286972",
    "assists": "0",
    "key_passes": "4",
    "npg": "0",
    "npxG": "0",
    "xGChain": "0.3535997271537781",
    "xGBuildup": "0.31216761469841003"
  },
  {
    "goals": "0",
    "shots": "0",
    "xG": "0",
    "time": "29",
    "position": "Sub",
    "h_team": "Union Berlin",
    "a_team": "Bayern Munich",
    "h_goals": "1",
    "a_goals": "5",
    "date": "2024-04-20",
    "id": "23327",
    "season": "2023",
    "roster_id": "655027",
    "xA": "0.046827372163534164",
    "assists": "0",
    "key_passes": "1",
    "npg": "0",
    "npxG": "0",
    "xGChain": "0.19702784717082977",
    "xGBuildup": "0.19702784717082977"
  },
  {
    "goals": "0",
    "shots": "0",
    "xG": "0",
    "time": "20",
    "position": "Sub",
    "h_team": "Union Berlin",
    "a_team": "Bayer Leverkusen",
    "h_goals": "0",
    "a_goals": "1",
    "date": "2024-04-06",
    "id": "23309",
    "season": "2023",
    "roster_id": "651628",
    "xA": "0.06245454400777817",
    "assists": "0",
    "key_passes": "4",
    "npg": "0",
    "npxG": "0",
    "xGChain": "0",
    "xGBuildup": "0"
  },
  {
    "goals": "0",
    "shots": "0",
    "xG": "0",
    "time": "8",
    "position": "Sub",
    "h_team": "Eintracht Frankfurt",
    "a_team": "Union Berlin",
    "h_goals": "0",
    "a_goals": "0",
    "date": "2024-03-30",
    "id": "23302",
    "season": "2023",
    "roster_id": "649671",
    "xA": "0",
    "assists": "0",
    "key_passes": "0",
    "npg": "0",
    "npxG": "0",
    "xGChain": "0",
    "xGBuildup": "0"
  },
  {
    "goals": "0",
    "shots": "0",
    "xG": "0",
    "time": "90",
    "position": "DR",
    "h_team": "VfB Stuttgart",
    "a_team": "Union Berlin",
    "h_goals": "2",
    "a_goals": "0",
    "date": "2024-03-08",
    "id": "23289",
    "season": "2023",
    "roster_id": "646171",
    "xA": "0.13353213667869568",
    "assists": "0",
    "key_passes": "2",
    "npg": "0",
    "npxG": "0",
    "xGChain": "0.02437063492834568",
    "xGBuildup": "0"
  },
  {
    "goals": "0",
    "shots": "0",
    "xG": "0",
    "time": "90",
    "position": "DMR",
    "h_team": "Union Berlin",
    "a_team": "Borussia Dortmund",
    "h_goals": "0",
    "a_goals": "2",
    "date": "2024-03-02",
    "id": "23272",
    "season": "2023",
    "roster_id": "644783",
    "xA": "0",
    "assists": "0",
    "key_passes": "0",
    "npg": "0",
    "npxG": "0",
    "xGChain": "0.04854406788945198",
    "xGBuildup": "0.04854406788945198"
  },
  {
    "goals": "0",
    "shots": "1",
    "xG": "0.026050332933664322",
    "time": "75",
    "position": "DMR",
    "h_team": "Union Berlin",
    "a_team": "FC Heidenheim",
    "h_goals": "2",
    "a_goals": "2",
    "date": "2024-02-24",
    "id": "23269",
    "season": "2023",
    "roster_id": "643114",
    "xA": "0.2531518042087555",
    "assists": "0",
    "key_passes": "2",
    "npg": "0",
    "npxG": "0.026050332933664322",
    "xGChain": "0.026050332933664322",
    "xGBuildup": "0"
  },
  {
    "goals": "0",
    "shots": "1",
    "xG": "0.0742085874080658",
    "time": "1",
    "position": "Sub",
    "h_team": "Hoffenheim",
    "a_team": "Union Berlin",
    "h_goals": "0",
    "a_goals": "1",
    "date": "2024-02-17",
    "id": "23259",
    "season": "2023",
    "roster_id": "641694",
    "xA": "0",
    "assists": "0",
    "key_passes": "0",
    "npg": "0",
    "npxG": "0.0742085874080658",
    "xGChain": "0",
    "xGBuildup": "0"
  },
  {
    "goals": "0",
    "shots": "3",
    "xG": "0.0923880785703659",
    "time": "89",
    "position": "DR",
    "h_team": "Freiburg",
    "a_team": "Union Berlin",
    "h_goals": "0",
    "a_goals": "0",
    "date": "2024-01-13",
    "id": "23211",
    "season": "2023",
    "roster_id": "634780",
    "xA": "0.22986027598381042",
    "assists": "0",
    "key_passes": "3",
    "npg": "0",
    "npxG": "0.0923880785703659",
    "xGChain": "0.20560134947299957",
    "xGBuildup": "0"
  },
  {
    "goals": "0",
    "shots": "1",
    "xG": "0.06864253431558609",
    "time": "90",
    "position": "DR",
    "h_team": "Union Berlin",
    "a_team": "FC Cologne",
    "h_goals": "2",
    "a_goals": "0",
    "date": "2023-12-20",
    "id": "23201",
    "season": "2023",
    "roster_id": "631631",
    "xA": "0",
    "assists": "0",
    "key_passes": "0",
    "npg": "0",
    "npxG": "0.06864253431558609",
    "xGChain": "0.38312584161758423",
    "xGBuildup": "0.31448331475257874"
  },
  {
    "goals": "0",
    "shots": "0",
    "xG": "0",
    "time": "90",
    "position": "DR",
    "h_team": "Bochum",
    "a_team": "Union Berlin",
    "h_goals": "3",
    "a_goals": "0",
    "date": "2023-12-16",
    "id": "23197",
    "season": "2023",
    "roster_id": "630222",
    "xA": "0.12886492908000946",
    "assists": "0",
    "key_passes": "2",
    "npg": "0",
    "npxG": "0",
    "xGChain": "0.07162975519895554",
    "xGBuildup": "0.07162975519895554"
  },
  {
    "goals": "0",
    "shots": "2",
    "xG": "0.17899999022483826",
    "time": "90",
    "position": "DR",
    "h_team": "Union Berlin",
    "a_team": "Borussia M.Gladbach",
    "h_goals": "3",
    "a_goals": "1",
    "date": "2023-12-09",
    "id": "23183",
    "season": "2023",
    "roster_id": "628599",
    "xA": "0.530868649482727",
    "assists": "0",
    "key_passes": "3",
    "npg": "0",
    "npxG": "0.17899999022483826",
    "xGChain": "0.5305368304252625",
    "xGBuildup": "0.029685834422707558"
  },
  {
    "goals": "0",
    "shots": "0",
    "xG": "0",
    "time": "9",
    "position": "Sub",
    "h_team": "Union Berlin",
    "a_team": "Augsburg",
    "h_goals": "1",
    "a_goals": "1",
    "date": "2023-11-25",
    "id": "23165",
    "season": "2023",
    "roster_id": "624787",
    "xA": "0",
    "assists": "0",
    "key_passes": "0",
    "npg": "0",
    "npxG": "0",
    "xGChain": "0",
    "xGBuildup": "0"
  },
  {
    "goals": "0",
    "shots": "0",
    "xG": "0",
    "time": "48",
    "position": "DMR",
    "h_team": "Bayer Leverkusen",
    "a_team": "Union Berlin",
    "h_goals": "4",
    "a_goals": "0",
    "date": "2023-11-12",
    "id": "23157",
    "season": "2023",
    "roster_id": "624037",
    "xA": "0",
    "assists": "0",
    "key_passes": "0",
    "npg": "0",
    "npxG": "0",
    "xGChain": "0",
    "xGBuildup": "0"
  },
  {
    "goals": "0",
    "shots": "1",
    "xG": "0.08502820134162903",
    "time": "90",
    "position": "DMR",
    "h_team": "Union Berlin",
    "a_team": "Hoffenheim",
    "h_goals": "0",
    "a_goals": "2",
    "date": "2023-09-23",
    "id": "23106",
    "season": "2023",
    "roster_id": "611966",
    "xA": "0.399152547121048",
    "assists": "0",
    "key_passes": "6",
    "npg": "0",
    "npxG": "0.08502820134162903",
    "xGChain": "0.6021153926849365",
    "xGBuildup": "0.30629146099090576"
  },
  {
    "goals": "0",
    "shots": "0",
    "xG": "0",
    "time": "15",
    "position": "Sub",
    "h_team": "Wolfsburg",
    "a_team": "Union Berlin",
    "h_goals": "2",
    "a_goals": "1",
    "date": "2023-09-16",
    "id": "23095",
    "season": "2023",
    "roster_id": "610238",
    "xA": "0.04288840666413307",
    "assists": "0",
    "key_passes": "2",
    "npg": "0",
    "npxG": "0",
    "xGChain": "0.27579572796821594",
    "xGBuildup": "0.27579572796821594"
  },
  {
    "goals": "0",
    "shots": "0",
    "xG": "0",
    "time": "72",
    "position": "DMR",
    "h_team": "Union Berlin",
    "a_team": "RasenBallsport Leipzig",
    "h_goals": "0",
    "a_goals": "3",
    "date": "2023-09-03",
    "id": "23091",
    "season": "2023",
    "roster_id": "609616",
    "xA": "0",
    "assists": "0",
    "key_passes": "0",
    "npg": "0",
    "npxG": "0",
    "xGChain": "0.10315264016389847",
    "xGBuildup": "0.10315264016389847"
  },
  {
    "goals": "0",
    "shots": "0",
    "xG": "0",
    "time": "90",
    "position": "DMR",
    "h_team": "Darmstadt",
    "a_team": "Union Berlin",
    "h_goals": "1",
    "a_goals": "4",
    "date": "2023-08-26",
    "id": "23079",
    "season": "2023",
    "roster_id": "606725",
    "xA": "0.6778555512428284",
    "assists": "2",
    "key_passes": "4",
    "npg": "0",
    "npxG": "0",
    "xGChain": "0.07963690906763077",
    "xGBuildup": "0.07963690906763077"
  },
  {
    "goals": "0",
    "shots": "0",
    "xG": "0",
    "time": "8",
    "position": "Sub",
    "h_team": "Union Berlin",
    "a_team": "Werder Bremen",
    "h_goals": "1",
    "a_goals": "0",
    "date": "2023-05-27",
    "id": "19641",
    "season": "2022",
    "roster_id": "600151",
    "xA": "0.05987397953867912",
    "assists": "0",
    "key_passes": "2",
    "npg": "0",
    "npxG": "0",
    "xGChain": "0.05987397953867912",
    "xGBuildup": "0"
  },
  {
    "goals": "0",
    "shots": "1",
    "xG": "0.05230013653635979",
    "time": "13",
    "position": "Sub",
    "h_team": "Hoffenheim",
    "a_team": "Union Berlin",
    "h_goals": "4",
    "a_goals": "2",
    "date": "2023-05-20",
    "id": "19634",
    "season": "2022",
    "roster_id": "598080",
    "xA": "0.13185207545757294",
    "assists": "0",
    "key_passes": "3",
    "npg": "0",
    "npxG": "0.05230013653635979",
    "xGChain": "0.17832696437835693",
    "xGBuildup": "0.0780288353562355"
  },
  {
    "goals": "0",
    "shots": "0",
    "xG": "0",
    "time": "90",
    "position": "DMR",
    "h_team": "Augsburg",
    "a_team": "Union Berlin",
    "h_goals": "1",
    "a_goals": "0",
    "date": "2023-05-06",
    "id": "19618",
    "season": "2022",
    "roster_id": "594661",
    "xA": "0.1614052951335907",
    "assists": "0",
    "key_passes": "3",
    "npg": "0",
    "npxG": "0",
    "xGChain": "0.2318378984928131",
    "xGBuildup": "0.162140890955925"
  },
  {
    "goals": "0",
    "shots": "0",
    "xG": "0",
    "time": "90",
    "position": "DMR",
    "h_team": "Union Berlin",
    "a_team": "Bayer Leverkusen",
    "h_goals": "0",
    "a_goals": "0",
    "date": "2023-04-29",
    "id": "19605",
    "season": "2022",
    "roster_id": "592208",
    "xA": "0.13764330744743347",
    "assists": "0",
    "key_passes": "2",
    "npg": "0",
    "npxG": "0",
    "xGChain": "0",
    "xGBuildup": "0"
  },
  {
    "goals": "0",
    "shots": "2",
    "xG": "0.0687216967344284",
    "time": "90",
    "position": "DMR",
    "h_team": "Borussia M.Gladbach",
    "a_team": "Union Berlin",
    "h_goals": "0",
    "a_goals": "1",
    "date": "2023-04-23",
    "id": "19599",
    "season": "2022",
    "roster_id": "591184",
    "xA": "0.12199035286903381",
    "assists": "0",
    "key_passes": "3",
    "npg": "0",
    "npxG": "0.0687216967344284",
    "xGChain": "0.140848770737648",
    "xGBuildup": "0.026568632572889328"
  },
  {
    "goals": "1",
    "shots": "1",
    "xG": "0.06608539819717407",
    "time": "90",
    "position": "DMR",
    "h_team": "Union Berlin",
    "a_team": "Bochum",
    "h_goals": "1",
    "a_goals": "1",
    "date": "2023-04-16",
    "id": "19587",
    "season": "2022",
    "roster_id": "589315",
    "xA": "0.20353099703788757",
    "assists": "0",
    "key_passes": "4",
    "npg": "1",
    "npxG": "0.06608539819717407",
    "xGChain": "0.7089390158653259",
    "xGBuildup": "0.7089390158653259"
  },
  {
    "goals": "0",
    "shots": "0",
    "xG": "0",
    "time": "90",
    "position": "DMR",
    "h_team": "Borussia Dortmund",
    "a_team": "Union Berlin",
    "h_goals": "2",
    "a_goals": "1",
    "date": "2023-04-08",
    "id": "19576",
    "season": "2022",
    "roster_id": "586643",
    "xA": "0",
    "assists": "0",
    "key_passes": "0",
    "npg": "0",
    "npxG": "0",
    "xGChain": "0",
    "xGBuildup": "0"
  },
  {
    "goals": "0",
    "shots": "0",
    "xG": "0",
    "time": "90",
    "position": "DMR",
    "h_team": "Union Berlin",
    "a_team": "Eintracht Frankfurt",
    "h_goals": "2",
    "a_goals": "0",
    "date": "2023-03-19",
    "id": "19560",
    "season": "2022",
    "roster_id": "583851",
    "xA": "0.01660050079226494",
    "assists": "0",
    "key_passes": "1",
    "npg": "0",
    "npxG": "0",
    "xGChain": "0.01660050079226494",
    "xGBuildup": "0.01660050079226494"
  },
  {
    "goals": "1",
    "shots": "1",
    "xG": "0.7577769756317139",
    "time": "90",
    "position": "DMR",
    "h_team": "Wolfsburg",
    "a_team": "Union Berlin",
    "h_goals": "1",
    "a_goals": "1",
    "date": "2023-03-12",
    "id": "19554",
    "season": "2022",
    "roster_id": "582317",
    "xA": "0.1357409954071045",
    "assists": "0",
    "key_passes": "3",
    "npg": "0",
    "npxG": "0",
    "xGChain": "0.11611700057983398",
    "xGBuildup": "0.05495870113372803"
  },
  {
    "goals": "0",
    "shots": "1",
    "xG": "0.04664609953761101",
    "time": "90",
    "position": "DML",
    "h_team": "Union Berlin",
    "a_team": "FC Cologne",
    "h_goals": "0",
    "a_goals": "0",
    "date": "2023-03-04",
    "id": "19542",
    "season": "2022",
    "roster_id": "579425",
    "xA": "0",
    "assists": "0",
    "key_passes": "0",
    "npg": "0",
    "npxG": "0.04664609953761101",
    "xGChain": "0.10262099653482437",
    "xGBuildup": "0.055974699556827545"
  },
  {
    "goals": "0",
    "shots": "1",
    "xG": "0.15988999605178833",
    "time": "90",
    "position": "DMR",
    "h_team": "RasenBallsport Leipzig",
    "a_team": "Union Berlin",
    "h_goals": "1",
    "a_goals": "2",
    "date": "2023-02-11",
    "id": "19514",
    "season": "2022",
    "roster_id": "575103",
    "xA": "0",
    "assists": "0",
    "key_passes": "0",
    "npg": "0",
    "npxG": "0.15988999605178833",
    "xGChain": "0.15988999605178833",
    "xGBuildup": "0"
  },
  {
    "goals": "0",
    "shots": "0",
    "xG": "0",
    "time": "90",
    "position": "DMR",
    "h_team": "Werder Bremen",
    "a_team": "Union Berlin",
    "h_goals": "1",
    "a_goals": "2",
    "date": "2023-01-25",
    "id": "19494",
    "season": "2022",
    "roster_id": "571291",
    "xA": "0.11579299718141556",
    "assists": "1",
    "key_passes": "1",
    "npg": "0",
    "npxG": "0",
    "xGChain": "0",
    "xGBuildup": "0"
  }
]